LICENSE
textual_datepicker/__init__.py
textual_datepicker/_date_picker.py
textual_datepicker/_date_select.py
textual_datepicker-0.2.3.dist-info/LICENSE
textual_datepicker-0.2.3.dist-info/WHEEL
textual_datepicker-0.2.3.dist-info/METADATA
textual_datepicker-0.2.3.dist-info/RECORD
