Metadata-Version: 2.1
Name: textual-datepicker
Version: 0.2.3
Summary: A datepicker widget for Textual.
Home-page: https://github.com/mitosch/textual-datepicker
License: MIT
Keywords: textual,textual datepicker,textual dateselect
Author: Mischa Schindowski
Author-email: mschindowski@gmail.com
Requires-Python: >=3.7,<4.0
Classifier: Development Status :: 4 - Beta
Classifier: Environment :: Console
Classifier: Intended Audience :: Developers
Classifier: License :: OSI Approved :: MIT License
Classifier: Operating System :: MacOS
Classifier: Operating System :: Microsoft :: Windows :: Windows 10
Classifier: Operating System :: Microsoft :: Windows :: Windows 11
Classifier: Operating System :: POSIX :: Linux
Classifier: Programming Language :: Python :: 3
Classifier: Programming Language :: Python :: 3.7
Classifier: Programming Language :: Python :: 3.8
Classifier: Programming Language :: Python :: 3.9
Classifier: Programming Language :: Python :: 3.10
Classifier: Programming Language :: Python :: 3.11
Requires-Dist: pendulum
Requires-Dist: textual (>=0.10.0,<0.11.0)
Project-URL: Repository, https://github.com/mitosch/textual-datepicker
